README.md
setup.py
pycloudmusic/__init__.py
pycloudmusic/ahttp.py
pycloudmusic/baseclass.py
pycloudmusic/error.py
pycloudmusic/music163.py
pycloudmusic/tools.py
pycloudmusic.egg-info/PKG-INFO
pycloudmusic.egg-info/SOURCES.txt
pycloudmusic.egg-info/dependency_links.txt
pycloudmusic.egg-info/requires.txt
pycloudmusic.egg-info/top_level.txt
pycloudmusic/object/__init__.py
pycloudmusic/object/music163.py