Metadata-Version: 2.1
Name: pycloudmusic
Version: 0.1.4
Summary: 优雅的异步高性能 Python 音乐 API 库 (网易云音乐)
Home-page: https://github.com/FengLiuFeseliud/pycloudmusic
Author: FengLiuFeseliud
Author-email: 17351198406@qq.com
License: UNKNOWN
Keywords: cloudmusic,asyncio,netease-cloud-music,netease,api
Platform: any
Classifier: Programming Language :: Python :: 3
Classifier: License :: OSI Approved :: MIT License
Classifier: Operating System :: OS Independent
Requires-Python: >=3.9
